treedisksegmentation/__init__.py
treedisksegmentation/cli.py
treedisksegmentation/config.py
treedisksegmentation/main.py
treedisksegmentation/models/__init__.py
treedisksegmentation/models/yolo.py
treedisksegmentation/segmentation/__init__.py
treedisksegmentation/segmentation/segmentation.py
treedisksegmentation/utils/__init__.py
treedisksegmentation/utils/file_utils.py
tree_disk_segmentation-0.2.2.dist-info/METADATA
tree_disk_segmentation-0.2.2.dist-info/WHEEL
tree_disk_segmentation-0.2.2.dist-info/entry_points.txt
tree_disk_segmentation-0.2.2.dist-info/RECORD
