Metadata-Version: 2.3
Name: tree-disk-segmentation
Version: 0.2.2
Summary: A package for tree disk segmentation in images
License: MIT
Keywords: tree,segmentation,image processing
Author: Tony
Author-email: tonymeissner70@gmail.com
Requires-Python: >=3.10
Classifier: License :: OSI Approved :: MIT License
Classifier: Programming Language :: Python :: 3
Classifier: Programming Language :: Python :: 3.10
Classifier: Programming Language :: Python :: 3.11
Classifier: Programming Language :: Python :: 3.12
Classifier: Programming Language :: Python :: 3.13
Requires-Dist: numpy (>=1.23.0,<2.0.0)
Requires-Dist: opencv-python (>=4.10.0.84,<5.0.0.0)
Requires-Dist: torch (>=2.5.1,<3.0.0)
Requires-Dist: torchvision (>=0.20.1,<0.21.0)
Requires-Dist: ultralytics (>=8.3.78,<9.0.0)
Project-URL: Homepage, https://github.com/tuke307/tree-disk-analyzer
Project-URL: Repository, https://github.com/tuke307/tree-disk-analyzer
